[
    {
        "features": [
            "vowel",
            "consonant",
            "prev1_vowel",
            "prev1_consonant",
            "prev2_vowel",
            "prev2_consonant",
            "prev3_vowel",
            "prev3_consonant",
            "next1_vowel",
            "next1_consonant",
            "next2_vowel",
            "next2_consonant",
            "next3_vowel",
            "next3_consonant",
            "is_syllabic_nasal",
            "is_sokuon",
            "elem_num",
            "mora_num",
            "elem_len",
            "mora_len_in_elem"
        ],
        "score": 0.7289293331271482
    },
    {
        "features": [
            "vowel",
            "consonant",
            "mora",
            "prev1_vowel",
            "prev1_consonant",
            "prev1_mora",
            "prev2_vowel",
            "prev2_consonant",
            "prev2_mora",
            "prev3_vowel",
            "prev3_consonant",
            "prev3_mora",
            "next1_vowel",
            "next1_consonant",
            "next1_mora",
            "next2_vowel",
            "next2_consonant",
            "next2_mora",
            "next3_vowel",
            "next3_consonant",
            "next3_mora",
            "is_syllabic_nasal",
            "is_sokuon",
            "elem_num",
            "mora_num",
            "elem_len",
            "mora_len_in_elem"
        ],
        "score": 0.7328744372451383
    },
    {
        "features": [
            "vowel",
            "consonant",
            "prev1_vowel",
            "prev1_consonant",
            "prev2_vowel",
            "prev2_consonant",
            "next1_vowel",
            "next1_consonant",
            "next2_vowel",
            "next2_consonant",
            "is_syllabic_nasal",
            "is_sokuon",
            "elem_num",
            "mora_num",
            "elem_len",
            "mora_len_in_elem"
        ],
        "score": 0.722315712481129
    },
    {
        "features": [
            "vowel",
            "consonant",
            "mora",
            "prev1_vowel",
            "prev1_consonant",
            "prev1_mora",
            "prev2_vowel",
            "prev2_consonant",
            "prev2_mora",
            "prev3_mora",
            "next1_vowel",
            "next1_consonant",
            "next1_mora",
            "next2_vowel",
            "next2_consonant",
            "next2_mora",
            "next3_mora",
            "is_syllabic_nasal",
            "is_sokuon",
            "elem_num",
            "mora_num",
            "elem_len",
            "mora_len_in_elem"
        ],
        "score": 0.7308031614671986
    },
    {
        "features": [
            "vowel",
            "consonant",
            "mora",
            "prev1_vowel",
            "prev1_consonant",
            "prev1_mora",
            "prev2_vowel",
            "prev2_consonant",
            "prev2_mora",
            "prev3_vowel",
            "prev3_consonant",
            "prev3_mora",
            "next1_vowel",
            "next1_consonant",
            "next1_mora",
            "next2_vowel",
            "next2_consonant",
            "next2_mora",
            "next3_vowel",
            "next3_consonant",
            "next3_mora",
            "is_syllabic_nasal",
            "is_sokuon",
            "is_long",
            "elem_num",
            "mora_num",
            "elem_len",
            "mora_len_in_elem"
        ],
        "score": 0.7342626286129812
    },
    {
        "features": [
            "vowel",
            "consonant",
            "mora",
            "prev1_vowel",
            "prev1_consonant",
            "prev1_mora",
            "prev2_vowel",
            "prev2_consonant",
            "prev2_mora",
            "prev3_vowel",
            "prev3_consonant",
            "prev3_mora",
            "next1_vowel",
            "next1_consonant",
            "next1_mora",
            "next2_vowel",
            "next2_consonant",
            "next2_mora",
            "next3_vowel",
            "next3_consonant",
            "next3_mora",
            "is_syllabic_nasal",
            "is_sokuon",
            "is_long",
            "next_is_syllabic_nasal",
            "next_is_sokuon",
            "next_is_long",
            "prev_is_syllabic_nasal",
            "prev_is_sokuon",
            "prev_is_long",
            "elem_num",
            "mora_num",
            "elem_len",
            "mora_len_in_elem"
        ],
        "score": 0.7358603413100994
    },
    {
        "features": [
            "vowel",
            "consonant",
            "mora",
            "prev1_vowel",
            "prev1_consonant",
            "prev1_mora",
            "prev2_vowel",
            "prev2_consonant",
            "prev2_mora",
            "prev3_vowel",
            "prev3_consonant",
            "prev3_mora",
            "next1_vowel",
            "next1_consonant",
            "next1_mora",
            "next2_vowel",
            "next2_consonant",
            "next2_mora",
            "next3_vowel",
            "next3_consonant",
            "next3_mora",
            "is_syllabic_nasal",
            "is_sokuon",
            "is_long",
            "next_is_syllabic_nasal",
            "next_is_sokuon",
            "next_is_long",
            "prev_is_syllabic_nasal",
            "prev_is_sokuon",
            "prev_is_long",
            "elem_num",
            "mora_num",
            "elem_len",
            "mora_len_in_elem",
            "total_mora_len"
        ],
        "score": 0.7364833682979709
    },
    {
        "features": [
            "vowel",
            "consonant",
            "mora",
            "prev1_vowel",
            "prev1_consonant",
            "prev1_mora",
            "prev2_vowel",
            "prev2_consonant",
            "prev2_mora",
            "prev3_vowel",
            "prev3_consonant",
            "prev3_mora",
            "next1_vowel",
            "next1_consonant",
            "next1_mora",
            "next2_vowel",
            "next2_consonant",
            "next2_mora",
            "next3_vowel",
            "next3_consonant",
            "next3_mora",
            "is_syllabic_nasal",
            "is_sokuon",
            "is_long",
            "next_is_syllabic_nasal",
            "next_is_sokuon",
            "next_is_long",
            "prev_is_syllabic_nasal",
            "prev_is_sokuon",
            "prev_is_long",
            "elem_num",
            "mora_num",
            "elem_len",
            "mora_len_in_elem",
            "total_mora_len"
        ],
        "score": 0.7345283340006047
    },
    {
        "features": [
            "vowel",
            "consonant",
            "mora",
            "prev1_vowel",
            "prev1_consonant",
            "prev1_mora",
            "prev2_vowel",
            "prev2_consonant",
            "prev2_mora",
            "prev3_vowel",
            "prev3_consonant",
            "prev3_mora",
            "next1_vowel",
            "next1_consonant",
            "next1_mora",
            "next2_vowel",
            "next2_consonant",
            "next2_mora",
            "next3_vowel",
            "next3_consonant",
            "next3_mora",
            "is_syllabic_nasal",
            "is_sokuon",
            "is_long",
            "next_is_syllabic_nasal",
            "next_is_sokuon",
            "next_is_long",
            "prev_is_syllabic_nasal",
            "prev_is_sokuon",
            "prev_is_long",
            "elem_num",
            "mora_num",
            "elem_len",
            "mora_len_in_elem",
            "total_mora_len"
        ],
        "score": 0.7345283340006047
    }
]